material_model/__init__.py
material_model/aac-bom.yaml
material_model/material_model_impl.py
material_model/no_circular_references.py
material_model/referenced_material_exists.py
aac_bom-0.0.4.dist-info/METADATA
aac_bom-0.0.4.dist-info/WHEEL
aac_bom-0.0.4.dist-info/entry_points.txt
aac_bom-0.0.4.dist-info/top_level.txt
aac_bom-0.0.4.dist-info/RECORD
