Metadata-Version: 2.1
Name: aac-bom
Version: 0.0.4
Summary: Architecture-as-Code (AaC) plugin for material modeling.  Rigorously track your sites, assemblies, and parts.
Home-page: UNKNOWN
License: MIT
Platform: UNKNOWN
Requires-Dist: aac ~=0.2.0
Provides-Extra: all
Requires-Dist: pipdeptree ~=2.13.0 ; extra == 'all'
Requires-Dist: wheel ~=0.41.0 ; extra == 'all'
Requires-Dist: pip-tools >=6.9.0 ; extra == 'all'
Requires-Dist: tox >=3.24 ; extra == 'all'
Requires-Dist: nose2 ~=0.10.0 ; extra == 'all'
Requires-Dist: coverage ~=6.0 ; extra == 'all'
Requires-Dist: flake8 ~=4.0 ; extra == 'all'
Requires-Dist: flake8-docstrings ~=1.6.0 ; extra == 'all'
Requires-Dist: flake8-fixme ~=1.1.1 ; extra == 'all'
Requires-Dist: flake8-eradicate ~=1.2.0 ; extra == 'all'
Requires-Dist: flake8-assertive ~=1.3.0 ; extra == 'all'
Provides-Extra: dev
Requires-Dist: pipdeptree ~=2.13.0 ; extra == 'dev'
Requires-Dist: wheel ~=0.41.0 ; extra == 'dev'
Requires-Dist: pip-tools >=6.9.0 ; extra == 'dev'
Provides-Extra: test
Requires-Dist: tox >=3.24 ; extra == 'test'
Requires-Dist: nose2 ~=0.10.0 ; extra == 'test'
Requires-Dist: coverage ~=6.0 ; extra == 'test'
Requires-Dist: flake8 ~=4.0 ; extra == 'test'
Requires-Dist: flake8-docstrings ~=1.6.0 ; extra == 'test'
Requires-Dist: flake8-fixme ~=1.1.1 ; extra == 'test'
Requires-Dist: flake8-eradicate ~=1.2.0 ; extra == 'test'
Requires-Dist: flake8-assertive ~=1.3.0 ; extra == 'test'
